MyPocket/DataPrep.py
MyPocket/__init__.py
MyPocket/utils.py
MyPocket-0.1.1.dist-info/LICENSE
MyPocket-0.1.1.dist-info/METADATA
MyPocket-0.1.1.dist-info/WHEEL
MyPocket-0.1.1.dist-info/top_level.txt
MyPocket-0.1.1.dist-info/RECORD
