Metadata-Version: 2.1
Name: MyPocket
Version: 0.1.1
Summary: Collect some interesting computation tools
Home-page: https://github.com/yuemolin/ToolBox
Author: Molin Yue
Author-email: yuemolin@umich.edu
License: MIT
Requires-Python: >=3.9
License-File: LICENSE
